vilpi/__init__.py
vilpi/visualty.py
vilpi-0.1.dist-info/METADATA
vilpi-0.1.dist-info/WHEEL
vilpi-0.1.dist-info/top_level.txt
vilpi-0.1.dist-info/RECORD
