Metadata-Version: 2.1
Name: vilpi
Version: 0.1
Summary: Python package for visualizing PyTorch models
Home-page: https://github.com/dykyivladk1/vilpi
Author: Vladyslav
Author-email: vladdikiy17@gmail.com
Classifier: Programming Language :: Python :: 3
Classifier: License :: OSI Approved :: MIT License
Classifier: Operating System :: OS Independent
Requires-Dist: matplotlib
Requires-Dist: torch
